lgraph.cpython-36m-x86_64-linux-gnu.so
lgraph-0.1.3.dist-info/METADATA
lgraph-0.1.3.dist-info/RECORD
lgraph-0.1.3.dist-info/WHEEL
lgraph-0.1.3.dist-info/top_level.txt
