Metadata-Version: 2.1
Name: lgraph
Version: 0.1.3
Summary: A test project using pybind11
Home-page: https://github.com/pybind/lgraph
Author: Sylvain Corlay
Author-email: sylvain.corlay@gmail.com
License: UNKNOWN
Platform: UNKNOWN
Requires-Dist: pybind11 (>=2.2)
